nubo/__init__.py
nubo/acquisition/__init__.py
nubo/acquisition/acquisition_function.py
nubo/acquisition/analytical.py
nubo/acquisition/monte_carlo.py
nubo/algorithms/__init__.py
nubo/algorithms/environmental_conditions.py
nubo/algorithms/optimise.py
nubo/models/__init__.py
nubo/models/fit.py
nubo/models/gaussian_process.py
nubo/optimisation/__init__.py
nubo/optimisation/adam.py
nubo/optimisation/lbfgsb.py
nubo/optimisation/mixed.py
nubo/optimisation/multipoint.py
nubo/optimisation/singlepoint.py
nubo/optimisation/slsqp.py
nubo/optimisation/utils.py
nubo/test_functions/__init__.py
nubo/test_functions/ackley.py
nubo/test_functions/dixonprice.py
nubo/test_functions/griewank.py
nubo/test_functions/hartmann.py
nubo/test_functions/levy.py
nubo/test_functions/rastrigin.py
nubo/test_functions/schwefel.py
nubo/test_functions/sphere.py
nubo/test_functions/sumsquares.py
nubo/test_functions/test_functions.py
nubo/test_functions/zakharov.py
nubo/utils/__init__.py
nubo/utils/generate_inputs.py
nubo/utils/latin_hypercube.py
nubo/utils/transform.py
nubopy-1.2.1.dist-info/licenses/LICENSE.md
nubopy-1.2.1.dist-info/METADATA
nubopy-1.2.1.dist-info/WHEEL
nubopy-1.2.1.dist-info/top_level.txt
nubopy-1.2.1.dist-info/RECORD
