Metadata-Version: 2.4
Name: nubopy
Version: 1.2.1
Summary: A transparent Python package for Bayesian optimisation
Author-email: Mike Diessner <m.diessner2@ncl.ac.uk>
Project-URL: Homepage, https://mikediessner.github.io/nubo
Classifier: Intended Audience :: Science/Research
Classifier: Programming Language :: Python :: 3
Requires-Python: >=3.10
License-File: LICENSE.md
Requires-Dist: torch>=2.0.0
Requires-Dist: gpytorch>=1.10
Requires-Dist: scipy>=1.10.0
Requires-Dist: numpy>=1.24.0
Dynamic: license-file
